imgplotter/__init__.py
imgplotter/point.py
imgplotter-0.0.1.dist-info/LICENSE
imgplotter-0.0.1.dist-info/METADATA
imgplotter-0.0.1.dist-info/WHEEL
imgplotter-0.0.1.dist-info/top_level.txt
imgplotter-0.0.1.dist-info/RECORD
