Metadata-Version: 2.1
Name: imgplotter
Version: 0.0.1
Summary: A small image package
Home-page: https://github.com/ShrishShukla/imgplotter
Author: Shrish Shukla
Author-email: shrish.shukla23@gmail.com
License: UNKNOWN
Project-URL: Github, https://github.com/ShrishShukla/imgplotter
Platform: UNKNOWN
Classifier: Programming Language :: Python :: 3
Classifier: License :: OSI Approved :: MIT License
Classifier: Operating System :: OS Independent
Requires-Python: >=3.6
